[
  {
    "title": "Kangaroo OMNI – Occlusion Alarm",
    "description": "Troubleshooting occlusion alarms",
    "assetType": "Feeding Pump",
    "manufacturer": "Cardinal Health",
    "model": "Kangaroo OMNI",
    "url": "guides/kangaroo-occlusion.html",
    "dateAdded": "2026-02-18"
  },
  {
    "title": "CADD Solis – Pump Not Priming",
    "description": "Step-by-step troubleshooting",
    "assetType": "Infusion Pump",
    "manufacturer": "Cardinal Health",
    "model": "CADD Solis",
    "url": "guides/cadd-solis-priming.html",
    "dateAdded": "2026-02-15"
  }
]

